GoodsimplePrinter/__init__.py
GoodsimplePrinter-1.0.0.dist-info/LICENSE.txt
GoodsimplePrinter-1.0.0.dist-info/METADATA
GoodsimplePrinter-1.0.0.dist-info/WHEEL
GoodsimplePrinter-1.0.0.dist-info/top_level.txt
GoodsimplePrinter-1.0.0.dist-info/RECORD
