Metadata-Version: 2.1
Name: GoodsimplePrinter
Version: 1.0.0
Summary: This is a simple printer with chooseable levels
Home-page: UNKNOWN
Author: Ankit Raturi
Author-email: ankitraturiak47@gmail.com
License: UNKNOWN
Platform: UNKNOWN
Classifier: Programming Language :: Python :: 3
Classifier: License :: OSI Approved :: MIT License
Classifier: Operating System :: OS Independent
License-File: LICENSE.txt
